nlp/__init__.py
nlp/imit_label_encoder.pkl
nlp/imit_main.py
nlp/imit_model.pkl
nlp/nlp_main.py
nlp/nlpmodel.pkl
nlp/nlpvectorizer.pkl
nlp/test_large.py
nlp/test_small.py
nlp_project-0.1.2.dist-info/LICENSE
nlp_project-0.1.2.dist-info/METADATA
nlp_project-0.1.2.dist-info/WHEEL
nlp_project-0.1.2.dist-info/top_level.txt
nlp_project-0.1.2.dist-info/RECORD
