Metadata-Version: 2.1
Name: nlp-project
Version: 0.1.2
Summary: A package for predicting buy and sell signals
Home-page: https://nkrtech.com
Author: Nicolus Rotich
Author-email: nicholas.rotich@gmail.com
License: MIT
Download-URL: https://github.com/moinonin/nlp_project/archive/refs/heads/main.zip
Platform: any
Classifier: License :: OSI Approved :: MIT License
Requires-Python: >=3.10
License-File: LICENSE
Requires-Dist: setuptools>=58.1.0
Requires-Dist: wheel>=0.37.1
Requires-Dist: scikit-learn>=1.4.0
Requires-Dist: imblearn==0.0
Requires-Dist: fire
Provides-Extra: dev
Requires-Dist: pytest; extra == "dev"
Requires-Dist: black; extra == "dev"
Requires-Dist: flake8; extra == "dev"
